seqwho_lib/__init__.py
seqwho_lib/seqwho.py
seqwho_lib/seqwho_buildindex.py
seqwho_lib/seqwho_modules.py
seqwho-1.0.3.dist-info/LICENSE
seqwho-1.0.3.dist-info/METADATA
seqwho-1.0.3.dist-info/WHEEL
seqwho-1.0.3.dist-info/entry_points.txt
seqwho-1.0.3.dist-info/top_level.txt
seqwho-1.0.3.dist-info/RECORD
