Metadata-Version: 2.1
Name: seqwho
Version: 1.0.3
Summary: Rapid and accurate classification of FASTQ(A) sequence files
Home-page: https://daehwankimlab.github.io/seqwho
Author: Christopher Bennett
Author-email: christopher.bennett@dshelix.net
License: GPLv3
Project-URL: Bug Tracker, https://github.com/DaehwanKimLab/Seqwho/issues
Project-URL: Documentation, https://daehwankimlab.github.io/seqwho/manual
Project-URL: Source Code, https://github.com/DaehwanKimLab/Seqwho
Platform: UNKNOWN
Requires-Python: >=3.7
License-File: LICENSE
Requires-Dist: joblib (==0.13.2)
Requires-Dist: numpy (==1.17.2)
Requires-Dist: pandas (==0.25.1)
Requires-Dist: seaborn (==0.9.0)
Requires-Dist: matplotlib (==3.1.1)
Requires-Dist: scikit-learn (==0.21.3)
